{
    "id": "bundle--7d188f68-9b6d-40d8-96a6-667ce3677874",
    "objects": [
        {
            "created": "2014-05-08T09:00:00.000Z",
            "id": "indicator--53fe3b22-0201-47cf-85d0-97c02164528d",
            "labels": [
                "ip-watchlist"
            ],
            "modified": "2014-05-08T09:00:00.000Z",
            "pattern": "[(email-message:subject = 'Fix The Error On Your Account.' AND email-message:from_ref.value = 'chase@ee.duke.edu' AND email-message:message_id = '201602112058.u1BKfrXh004925@mail-gw-01.oit.duke.edu') AND email-message:additional_header_fields.'X-Mailer' = 'Microsoft Outlook Express 6.00.2800.1437']",
            "type": "indicator",
            "valid_from": "2014-05-08T09:00:00.000000Z"
        },
        {
            "created": "2020-12-30T15:42:18.486Z",
            "first_observed": "2020-12-30T15:42:18.486Z",
            "id": "observed-data--6355649f-ad9a-4cc1-8edc-28effcf451c5",
            "last_observed": "2020-12-30T15:42:18.486Z",
            "modified": "2020-12-30T15:42:18.486Z",
            "number_observed": 1,
            "objects": {
                "0": {
                    "type": "url",
                    "value": "http://thereelin.com/mac/htm"
                }
            },
            "type": "observed-data"
        }
    ],
    "spec_version": "2.0",
    "type": "bundle"
}
